server.py
src/__init__.py
src/client/__init__.py
src/client/websocket_client.py
src/tools/__init__.py
src/tools/connection.py
src/tools/navigation.py
src/tools/notes_measures.py
src/tools/sequences.py
src/tools/staff_instruments.py
src/tools/time_tempo.py
src/types/__init__.py
src/types/action_types.py
iflow_mcp_ghchen99_mcp_musescore-0.1.0.dist-info/METADATA
iflow_mcp_ghchen99_mcp_musescore-0.1.0.dist-info/WHEEL
iflow_mcp_ghchen99_mcp_musescore-0.1.0.dist-info/entry_points.txt
iflow_mcp_ghchen99_mcp_musescore-0.1.0.dist-info/licenses/LICENSE
iflow_mcp_ghchen99_mcp_musescore-0.1.0.dist-info/RECORD
