Metadata-Version: 2.4
Name: iflow-mcp_ghchen99_mcp-musescore
Version: 0.1.0
Summary: MCP server for MuseScore control through WebSocket
License-File: LICENSE
Requires-Python: >=3.8
Requires-Dist: mcp>=1.0.0
Requires-Dist: websockets>=13.0
